git_diff_lines/__init__.py
git_diff_lines/git_diff_lines.py
git_diff_lines/parser.py
git_diff_lines-0.0.1.dist-info/LICENSE
git_diff_lines-0.0.1.dist-info/METADATA
git_diff_lines-0.0.1.dist-info/WHEEL
git_diff_lines-0.0.1.dist-info/top_level.txt
git_diff_lines-0.0.1.dist-info/RECORD
